proliferate/__init__.py
proliferate/api.py
proliferate/core/__init__.py
proliferate/core/client.py
proliferate/core/hub.py
proliferate/core/options.py
proliferate/core/scope.py
proliferate/instrumentation/__init__.py
proliferate/instrumentation/excepthook.py
proliferate/integrations/__init__.py
proliferate/integrations/base.py
proliferate/integrations/fastapi.py
proliferate/transport/__init__.py
proliferate/transport/base.py
proliferate/transport/http.py
proliferate/utils/__init__.py
proliferate/utils/release.py
proliferate_ai-0.2.2.dist-info/METADATA
proliferate_ai-0.2.2.dist-info/WHEEL
proliferate_ai-0.2.2.dist-info/RECORD
